popular_times/__init__.py
popular_times/geojson_processing.py
popular_times/get_place_data.py
popular_times/scrape_pt_data.py
popular_times-0.1.dist-info/DESCRIPTION.rst
popular_times-0.1.dist-info/METADATA
popular_times-0.1.dist-info/RECORD
popular_times-0.1.dist-info/WHEEL
popular_times-0.1.dist-info/metadata.json
popular_times-0.1.dist-info/top_level.txt
