Metadata-Version: 2.0
Name: popular-times
Version: 0.1
Summary: This package allows for retrieval of Google Popular Times data.
Home-page: http://github.com/apollojain/popular_times
Author: Adawgrhinopower
Author-email: apollojain@berkeley.edu
License: MIT
Platform: UNKNOWN
